{
  "task": "graph_anomaly",
  "dataset": "synth",
  "summary": {
    "0.4": {
      "pairwise_mean": 0.7083333333333334,
      "pairwise_std": 0.0,
      "fullget_mean": 1.0,
      "fullget_std": 0.0,
      "et_local_mean": 1.0,
      "et_local_std": 0.0,
      "et_complete_mean": 0.375,
      "et_complete_std": 0.0
    }
  },
  "runs": {
    "0.4": [
      {
        "seed": 123,
        "pairwise_auc": 0.7083333333333334,
        "fullget_auc": 1.0,
        "gin_auc": 1.0,
        "et_local_auc": 1.0,
        "et_complete_auc": 0.375,
        "histories": {
          "pairwise": {
            "train_loss": [
              0.7253747582435608
            ],
            "val_auc": [
              1.0
            ],
            "test_auc": [
              0.7083333333333334
            ],
            "bad_batches": [
              0
            ]
          },
          "fullget": {
            "train_loss": [
              0.7788571715354919
            ],
            "val_auc": [
              1.0
            ],
            "test_auc": [
              1.0
            ],
            "bad_batches": [
              0
            ]
          },
          "gin": {
            "train_loss": [
              0.4324682950973511
            ],
            "val_auc": [
              1.0
            ],
            "test_auc": [
              1.0
            ],
            "bad_batches": [
              0
            ]
          },
          "et_local": {
            "train_loss": [
              0.700861006975174
            ],
            "val_auc": [
              1.0
            ],
            "test_auc": [
              1.0
            ],
            "bad_batches": [
              0
            ]
          },
          "et_complete": {
            "train_loss": [
              0.8372616767883301
            ],
            "val_auc": [
              0.5
            ],
            "test_auc": [
              0.375
            ],
            "bad_batches": [
              0
            ]
          }
        }
      }
    ]
  }
}